harp/protocol/__init__.py
harp/protocol/base.py
harp/protocol/exceptions.py
harp/protocol/messages.py
harp_protocol-0.4.0.dist-info/WHEEL
harp_protocol-0.4.0.dist-info/METADATA
harp_protocol-0.4.0.dist-info/RECORD
